codetogpt/__init__.py
codetogpt/packager.py
code_to_gpt-0.6.dist-info/LICENSE
code_to_gpt-0.6.dist-info/METADATA
code_to_gpt-0.6.dist-info/WHEEL
code_to_gpt-0.6.dist-info/entry_points.txt
code_to_gpt-0.6.dist-info/top_level.txt
code_to_gpt-0.6.dist-info/RECORD
