Metadata-Version: 2.1
Name: code-to-gpt
Version: 0.6
Summary: A simple tool to concatenate code files for ChatGPT prompts
Home-page: https://github.com/yourusername/codepackager
Author: Sameel Shahid
Author-email: sameelshahid@hotmail.com
License: UNKNOWN
Platform: UNKNOWN
Classifier: Programming Language :: Python :: 3
Classifier: License :: OSI Approved :: MIT License
Classifier: Operating System :: OS Independent
Requires-Python: >=3.6
License-File: LICENSE
